{
  "project_info": {
    "project_number": "66995304796",
    "project_id": "surfriders-35b86",
    "storage_bucket": "surfriders-35b86.firebasestorage.app"
  },
  "client": [
    {
      "client_info": {
        "mobilesdk_app_id": "1:66995304796:android:02bb1fa9f038af4f5d6999",
        "android_client_info": {
          "package_name": "com.example.surfriders"
        }
      },
      "oauth_client": [],
      "api_key": [
        {
          "current_key": "AIzaSyDaCFFOAGEJhG_jt_HpwcfuxQvxZmWRcU4"
        }
      ],
      "services": {
        "appinvite_service": {
          "other_platform_oauth_client": []
        }
      }
    }
  ],
  "configuration_version": "1"
}